{"config":{"output_file":null,"full_docs":false,"pub_only":false,"reachable_only":false,"distro_crate":false,"signatures":false,"borrow_data":false},"version":"0.19.1","compilation":{"directory":"/home/nachiket/CP/stone_game","program":"/home/nachiket/.rustup/toolchains/stable-x86_64-unknown-linux-gnu/bin/rls","arguments":[],"output":"/home/nachiket/CP/stone_game/target/rls/debug/deps/libstone_game-9a370d5a0cc2a88d.rmeta"},"prelude":{"crate_id":{"name":"stone_game","disambiguator":[3426680261729636316,15479446576159134289]},"crate_root":"src","external_crates":[{"file_name":"/home/nachiket/CP/stone_game/src/main.rs","num":1,"id":{"name":"std","disambiguator":[16244594805693024294,13769610595479902485]}},{"file_name":"/home/nachiket/CP/stone_game/src/main.rs","num":2,"id":{"name":"core","disambiguator":[9461532395471723626,17649752992216879242]}},{"file_name":"/home/nachiket/CP/stone_game/src/main.rs","num":3,"id":{"name":"compiler_builtins","disambiguator":[13102141027849022754,10844956084955862736]}},{"file_name":"/home/nachiket/CP/stone_game/src/main.rs","num":4,"id":{"name":"rustc_std_workspace_core","disambiguator":[10802439125609973726,12056872925128751599]}},{"file_name":"/home/nachiket/CP/stone_game/src/main.rs","num":5,"id":{"name":"alloc","disambiguator":[10377672983135696745,6222977342718677897]}},{"file_name":"/home/nachiket/CP/stone_game/src/main.rs","num":6,"id":{"name":"libc","disambiguator":[12556834526510219591,10145975442274216472]}},{"file_name":"/home/nachiket/CP/stone_game/src/main.rs","num":7,"id":{"name":"unwind","disambiguator":[1920608168423631117,11305390197699278538]}},{"file_name":"/home/nachiket/CP/stone_game/src/main.rs","num":8,"id":{"name":"cfg_if","disambiguator":[14153420169627805217,3922141685752559776]}},{"file_name":"/home/nachiket/CP/stone_game/src/main.rs","num":9,"id":{"name":"hashbrown","disambiguator":[8992588241071530954,2055378767109441873]}},{"file_name":"/home/nachiket/CP/stone_game/src/main.rs","num":10,"id":{"name":"rustc_std_workspace_alloc","disambiguator":[6584924783227651491,7746393078969085327]}},{"file_name":"/home/nachiket/CP/stone_game/src/main.rs","num":11,"id":{"name":"rustc_demangle","disambiguator":[16866912217167506759,12404743428505733407]}},{"file_name":"/home/nachiket/CP/stone_game/src/main.rs","num":12,"id":{"name":"addr2line","disambiguator":[5891363554589716223,15364815277334307594]}},{"file_name":"/home/nachiket/CP/stone_game/src/main.rs","num":13,"id":{"name":"gimli","disambiguator":[15133864894733438722,17571364763769299029]}},{"file_name":"/home/nachiket/CP/stone_game/src/main.rs","num":14,"id":{"name":"object","disambiguator":[5376887079506337588,3050710466351220396]}},{"file_name":"/home/nachiket/CP/stone_game/src/main.rs","num":15,"id":{"name":"miniz_oxide","disambiguator":[3374711390048344050,17348866986865533303]}},{"file_name":"/home/nachiket/CP/stone_game/src/main.rs","num":16,"id":{"name":"adler","disambiguator":[16389676859204901274,11575250456210569958]}},{"file_name":"/home/nachiket/CP/stone_game/src/main.rs","num":17,"id":{"name":"panic_unwind","disambiguator":[4785159557203218631,3838940703516147450]}}],"span":{"file_name":"src/main.rs","byte_start":0,"byte_end":951,"line_start":1,"line_end":38,"column_start":1,"column_end":2}},"imports":[{"kind":"Use","ref_id":{"krate":1,"index":3170},"span":{"file_name":"src/main.rs","byte_start":9,"byte_end":11,"line_start":1,"line_end":1,"column_start":10,"column_end":12},"alias_span":null,"name":"io","value":"","parent":{"krate":0,"index":0}}],"defs":[{"kind":"Mod","id":{"krate":0,"index":0},"span":{"file_name":"src/main.rs","byte_start":0,"byte_end":951,"line_start":1,"line_end":38,"column_start":1,"column_end":2},"name":"","qualname":"::","value":"src/main.rs","parent":null,"children":[{"krate":0,"index":1},{"krate":0,"index":2},{"krate":0,"index":3},{"krate":0,"index":6},{"krate":0,"index":9}],"decl_id":null,"docs":"","sig":null,"attributes":[]},{"kind":"Function","id":{"krate":0,"index":6},"span":{"file_name":"src/main.rs","byte_start":17,"byte_end":26,"line_start":3,"line_end":3,"column_start":4,"column_end":13},"name":"read_line","qualname":"::read_line","value":"fn read_line() -> Vec<usize>","parent":null,"children":[],"decl_id":null,"docs":"","sig":null,"attributes":[]},{"kind":"Local","id":{"krate":0,"index":3758096390},"span":{"file_name":"src/main.rs","byte_start":57,"byte_end":61,"line_start":4,"line_end":4,"column_start":13,"column_end":17},"name":"line","qualname":"line$HirId { owner: DefId(0:6 ~ stone_game[2f8e]::read_line), local_id: 7 }","value":"std::string::String","parent":null,"children":[],"decl_id":null,"docs":"","sig":null,"attributes":[]},{"kind":"Local","id":{"krate":0,"index":67108870},"span":{"file_name":"src/main.rs","byte_start":180,"byte_end":184,"line_start":8,"line_end":8,"column_start":18,"column_end":22},"name":"line","qualname":"$HirId { owner: DefId(0:6 ~ stone_game[2f8e]::read_line), local_id: 40 }::line","value":"&&str","parent":null,"children":[],"decl_id":null,"docs":"","sig":null,"attributes":[]},{"kind":"Local","id":{"krate":0,"index":3556769798},"span":{"file_name":"src/main.rs","byte_start":216,"byte_end":219,"line_start":9,"line_end":9,"column_start":15,"column_end":18},"name":"val","qualname":"$HirId { owner: DefId(0:6 ~ stone_game[2f8e]::read_line), local_id: 55 }::val","value":"&str","parent":null,"children":[],"decl_id":null,"docs":"","sig":null,"attributes":[]},{"kind":"Function","id":{"krate":0,"index":9},"span":{"file_name":"src/main.rs","byte_start":284,"byte_end":288,"line_start":13,"line_end":13,"column_start":4,"column_end":8},"name":"main","qualname":"::main","value":"fn main()","parent":null,"children":[],"decl_id":null,"docs":"","sig":null,"attributes":[]},{"kind":"Local","id":{"krate":0,"index":3758096393},"span":{"file_name":"src/main.rs","byte_start":301,"byte_end":302,"line_start":14,"line_end":14,"column_start":9,"column_end":10},"name":"t","qualname":"t$HirId { owner: DefId(0:9 ~ stone_game[2f8e]::main), local_id: 7 }","value":"usize","parent":null,"children":[],"decl_id":null,"docs":"","sig":null,"attributes":[]},{"kind":"Local","id":{"krate":0,"index":3623878665},"span":{"file_name":"src/main.rs","byte_start":334,"byte_end":338,"line_start":15,"line_end":15,"column_start":14,"column_end":18},"name":"iter","qualname":"iter$HirId { owner: DefId(0:9 ~ stone_game[2f8e]::main), local_id: 27 }","value":"std::ops::Range<usize>","parent":null,"children":[],"decl_id":null,"docs":"","sig":null,"attributes":[]},{"kind":"Local","id":{"krate":0,"index":4026531849},"span":{"file_name":"src/main.rs","byte_start":334,"byte_end":338,"line_start":15,"line_end":15,"column_start":14,"column_end":18},"name":"__next","qualname":"__next$HirId { owner: DefId(0:9 ~ stone_game[2f8e]::main), local_id: 15 }","value":"usize","parent":null,"children":[],"decl_id":null,"docs":"","sig":null,"attributes":[]},{"kind":"Local","id":{"krate":0,"index":134217737},"span":{"file_name":"src/main.rs","byte_start":329,"byte_end":330,"line_start":15,"line_end":15,"column_start":9,"column_end":10},"name":"val","qualname":"val$HirId { owner: DefId(0:9 ~ stone_game[2f8e]::main), local_id: 16 }","value":"usize","parent":null,"children":[],"decl_id":null,"docs":"","sig":null,"attributes":[]},{"kind":"Local","id":{"krate":0,"index":1946157065},"span":{"file_name":"src/main.rs","byte_start":353,"byte_end":354,"line_start":16,"line_end":16,"column_start":13,"column_end":14},"name":"n","qualname":"n$HirId { owner: DefId(0:9 ~ stone_game[2f8e]::main), local_id: 46 }","value":"usize","parent":null,"children":[],"decl_id":null,"docs":"","sig":null,"attributes":[]},{"kind":"Local","id":{"krate":0,"index":738197513},"span":{"file_name":"src/main.rs","byte_start":385,"byte_end":386,"line_start":17,"line_end":17,"column_start":13,"column_end":14},"name":"a","qualname":"a$HirId { owner: DefId(0:9 ~ stone_game[2f8e]::main), local_id: 52 }","value":"std::vec::Vec<usize>","parent":null,"children":[],"decl_id":null,"docs":"","sig":null,"attributes":[]},{"kind":"Local","id":{"krate":0,"index":3523215369},"span":{"file_name":"src/main.rs","byte_start":449,"byte_end":452,"line_start":19,"line_end":19,"column_start":17,"column_end":20},"name":"ans","qualname":"ans$HirId { owner: DefId(0:9 ~ stone_game[2f8e]::main), local_id: 75 }","value":"usize","parent":null,"children":[],"decl_id":null,"docs":"","sig":null,"attributes":[]},{"kind":"Local","id":{"krate":0,"index":4194304009},"span":{"file_name":"src/main.rs","byte_start":475,"byte_end":479,"line_start":20,"line_end":20,"column_start":18,"column_end":22},"name":"iter","qualname":"iter$HirId { owner: DefId(0:9 ~ stone_game[2f8e]::main), local_id: 95 }","value":"std::ops::Range<usize>","parent":null,"children":[],"decl_id":null,"docs":"","sig":null,"attributes":[]},{"kind":"Local","id":{"krate":0,"index":3388997641},"span":{"file_name":"src/main.rs","byte_start":475,"byte_end":479,"line_start":20,"line_end":20,"column_start":18,"column_end":22},"name":"__next","qualname":"__next$HirId { owner: DefId(0:9 ~ stone_game[2f8e]::main), local_id: 83 }","value":"usize","parent":null,"children":[],"decl_id":null,"docs":"","sig":null,"attributes":[]},{"kind":"Local","id":{"krate":0,"index":704643081},"span":{"file_name":"src/main.rs","byte_start":470,"byte_end":471,"line_start":20,"line_end":20,"column_start":13,"column_end":14},"name":"val","qualname":"val$HirId { owner: DefId(0:9 ~ stone_game[2f8e]::main), local_id: 84 }","value":"usize","parent":null,"children":[],"decl_id":null,"docs":"","sig":null,"attributes":[]},{"kind":"Local","id":{"krate":0,"index":2516582409},"span":{"file_name":"src/main.rs","byte_start":470,"byte_end":471,"line_start":20,"line_end":20,"column_start":13,"column_end":14},"name":"i","qualname":"i$HirId { owner: DefId(0:9 ~ stone_game[2f8e]::main), local_id: 105 }","value":"usize","parent":null,"children":[],"decl_id":null,"docs":"","sig":null,"attributes":[]},{"kind":"Local","id":{"krate":0,"index":4261412873},"span":{"file_name":"src/main.rs","byte_start":503,"byte_end":507,"line_start":21,"line_end":21,"column_start":22,"column_end":26},"name":"iter","qualname":"iter$HirId { owner: DefId(0:9 ~ stone_game[2f8e]::main), local_id: 127 }","value":"std::ops::Range<usize>","parent":null,"children":[],"decl_id":null,"docs":"","sig":null,"attributes":[]},{"kind":"Local","id":{"krate":0,"index":3456106505},"span":{"file_name":"src/main.rs","byte_start":503,"byte_end":507,"line_start":21,"line_end":21,"column_start":22,"column_end":26},"name":"__next","qualname":"__next$HirId { owner: DefId(0:9 ~ stone_game[2f8e]::main), local_id: 115 }","value":"usize","parent":null,"children":[],"decl_id":null,"docs":"","sig":null,"attributes":[]},{"kind":"Local","id":{"krate":0,"index":771751945},"span":{"file_name":"src/main.rs","byte_start":498,"byte_end":499,"line_start":21,"line_end":21,"column_start":17,"column_end":18},"name":"val","qualname":"val$HirId { owner: DefId(0:9 ~ stone_game[2f8e]::main), local_id: 116 }","value":"usize","parent":null,"children":[],"decl_id":null,"docs":"","sig":null,"attributes":[]},{"kind":"Local","id":{"krate":0,"index":2432696329},"span":{"file_name":"src/main.rs","byte_start":498,"byte_end":499,"line_start":21,"line_end":21,"column_start":17,"column_end":18},"name":"j","qualname":"j$HirId { owner: DefId(0:9 ~ stone_game[2f8e]::main), local_id: 137 }","value":"usize","parent":null,"children":[],"decl_id":null,"docs":"","sig":null,"attributes":[]},{"kind":"Local","id":{"krate":0,"index":1895825417},"span":{"file_name":"src/main.rs","byte_start":534,"byte_end":536,"line_start":22,"line_end":22,"column_start":25,"column_end":27},"name":"ok","qualname":"ok$HirId { owner: DefId(0:9 ~ stone_game[2f8e]::main), local_id: 142 }","value":"bool","parent":null,"children":[],"decl_id":null,"docs":"","sig":null,"attributes":[]},{"kind":"Local","id":{"krate":0,"index":1157627913},"span":{"file_name":"src/main.rs","byte_start":570,"byte_end":575,"line_start":23,"line_end":23,"column_start":26,"column_end":31},"name":"iter","qualname":"iter$HirId { owner: DefId(0:9 ~ stone_game[2f8e]::main), local_id: 162 }","value":"std::ops::RangeInclusive<usize>","parent":null,"children":[],"decl_id":null,"docs":"","sig":null,"attributes":[]},{"kind":"Local","id":{"krate":0,"index":1761607689},"span":{"file_name":"src/main.rs","byte_start":570,"byte_end":575,"line_start":23,"line_end":23,"column_start":26,"column_end":31},"name":"__next","qualname":"__next$HirId { owner: DefId(0:9 ~ stone_game[2f8e]::main), local_id: 150 }","value":"usize","parent":null,"children":[],"decl_id":null,"docs":"","sig":null,"attributes":[]},{"kind":"Local","id":{"krate":0,"index":3909091337},"span":{"file_name":"src/main.rs","byte_start":565,"byte_end":566,"line_start":23,"line_end":23,"column_start":21,"column_end":22},"name":"val","qualname":"val$HirId { owner: DefId(0:9 ~ stone_game[2f8e]::main), local_id: 151 }","value":"usize","parent":null,"children":[],"decl_id":null,"docs":"","sig":null,"attributes":[]},{"kind":"Local","id":{"krate":0,"index":889192457},"span":{"file_name":"src/main.rs","byte_start":565,"byte_end":566,"line_start":23,"line_end":23,"column_start":21,"column_end":22},"name":"k","qualname":"k$HirId { owner: DefId(0:9 ~ stone_game[2f8e]::main), local_id: 172 }","value":"usize","parent":null,"children":[],"decl_id":null,"docs":"","sig":null,"attributes":[]}],"impls":[],"refs":[{"kind":"Mod","span":{"file_name":"src/main.rs","byte_start":4,"byte_end":7,"line_start":1,"line_end":1,"column_start":5,"column_end":8},"ref_id":{"krate":1,"index":0}},{"kind":"Type","span":{"file_name":"src/main.rs","byte_start":32,"byte_end":35,"line_start":3,"line_end":3,"column_start":19,"column_end":22},"ref_id":{"krate":5,"index":6703}},{"kind":"Function","span":{"file_name":"src/main.rs","byte_start":72,"byte_end":75,"line_start":4,"line_end":4,"column_start":28,"column_end":31},"ref_id":{"krate":5,"index":5207}},{"kind":"Type","span":{"file_name":"src/main.rs","byte_start":64,"byte_end":70,"line_start":4,"line_end":4,"column_start":20,"column_end":26},"ref_id":{"krate":5,"index":7216}},{"kind":"Function","span":{"file_name":"src/main.rs","byte_start":116,"byte_end":122,"line_start":5,"line_end":5,"column_start":38,"column_end":44},"ref_id":{"krate":2,"index":8079}},{"kind":"Function","span":{"file_name":"src/main.rs","byte_start":95,"byte_end":104,"line_start":5,"line_end":5,"column_start":17,"column_end":26},"ref_id":{"krate":1,"index":4029}},{"kind":"Function","span":{"file_name":"src/main.rs","byte_start":87,"byte_end":92,"line_start":5,"line_end":5,"column_start":9,"column_end":14},"ref_id":{"krate":1,"index":4023}},{"kind":"Mod","span":{"file_name":"src/main.rs","byte_start":83,"byte_end":85,"line_start":5,"line_end":5,"column_start":5,"column_end":7},"ref_id":{"krate":1,"index":3170}},{"kind":"Variable","span":{"file_name":"src/main.rs","byte_start":110,"byte_end":114,"line_start":5,"line_end":5,"column_start":32,"column_end":36},"ref_id":{"krate":0,"index":3758096390}},{"kind":"Function","span":{"file_name":"src/main.rs","byte_start":268,"byte_end":275,"line_start":10,"line_end":10,"column_start":10,"column_end":17},"ref_id":{"krate":2,"index":7218}},{"kind":"Function","span":{"file_name":"src/main.rs","byte_start":211,"byte_end":214,"line_start":9,"line_end":9,"column_start":10,"column_end":13},"ref_id":{"krate":2,"index":7180}},{"kind":"Function","span":{"file_name":"src/main.rs","byte_start":172,"byte_end":178,"line_start":8,"line_end":8,"column_start":10,"column_end":16},"ref_id":{"krate":2,"index":7190}},{"kind":"Function","span":{"file_name":"src/main.rs","byte_start":151,"byte_end":156,"line_start":7,"line_end":7,"column_start":10,"column_end":15},"ref_id":{"krate":2,"index":11542}},{"kind":"Function","span":{"file_name":"src/main.rs","byte_start":135,"byte_end":139,"line_start":6,"line_end":6,"column_start":10,"column_end":14},"ref_id":{"krate":2,"index":11581}},{"kind":"Variable","span":{"file_name":"src/main.rs","byte_start":130,"byte_end":134,"line_start":6,"line_end":6,"column_start":5,"column_end":9},"ref_id":{"krate":0,"index":3758096390}},{"kind":"Function","span":{"file_name":"src/main.rs","byte_start":191,"byte_end":194,"line_start":8,"line_end":8,"column_start":29,"column_end":32},"ref_id":{"krate":2,"index":11498}},{"kind":"Variable","span":{"file_name":"src/main.rs","byte_start":186,"byte_end":190,"line_start":8,"line_end":8,"column_start":24,"column_end":28},"ref_id":{"krate":0,"index":67108870}},{"kind":"Function","span":{"file_name":"src/main.rs","byte_start":249,"byte_end":255,"line_start":9,"line_end":9,"column_start":48,"column_end":54},"ref_id":{"krate":2,"index":8079}},{"kind":"Function","span":{"file_name":"src/main.rs","byte_start":232,"byte_end":237,"line_start":9,"line_end":9,"column_start":31,"column_end":36},"ref_id":{"krate":2,"index":11610}},{"kind":"Function","span":{"file_name":"src/main.rs","byte_start":225,"byte_end":229,"line_start":9,"line_end":9,"column_start":24,"column_end":28},"ref_id":{"krate":2,"index":11581}},{"kind":"Variable","span":{"file_name":"src/main.rs","byte_start":221,"byte_end":224,"line_start":9,"line_end":9,"column_start":20,"column_end":23},"ref_id":{"krate":0,"index":3556769798}},{"kind":"Function","span":{"file_name":"src/main.rs","byte_start":305,"byte_end":314,"line_start":14,"line_end":14,"column_start":13,"column_end":22},"ref_id":{"krate":0,"index":6}},{"kind":"Variable","span":{"file_name":"src/main.rs","byte_start":334,"byte_end":335,"line_start":15,"line_end":15,"column_start":14,"column_end":15},"ref_id":{"krate":2,"index":35951}},{"kind":"Variable","span":{"file_name":"src/main.rs","byte_start":337,"byte_end":338,"line_start":15,"line_end":15,"column_start":17,"column_end":18},"ref_id":{"krate":2,"index":35952}},{"kind":"Variable","span":{"file_name":"src/main.rs","byte_start":337,"byte_end":338,"line_start":15,"line_end":15,"column_start":17,"column_end":18},"ref_id":{"krate":0,"index":3758096393}},{"kind":"Variable","span":{"file_name":"src/main.rs","byte_start":329,"byte_end":330,"line_start":15,"line_end":15,"column_start":9,"column_end":10},"ref_id":{"krate":2,"index":37341}},{"kind":"Function","span":{"file_name":"src/main.rs","byte_start":357,"byte_end":366,"line_start":16,"line_end":16,"column_start":17,"column_end":26},"ref_id":{"krate":0,"index":6}},{"kind":"Function","span":{"file_name":"src/main.rs","byte_start":389,"byte_end":398,"line_start":17,"line_end":17,"column_start":17,"column_end":26},"ref_id":{"krate":0,"index":6}},{"kind":"Function","span":{"file_name":"src/main.rs","byte_start":420,"byte_end":423,"line_start":18,"line_end":18,"column_start":19,"column_end":22},"ref_id":{"krate":5,"index":6781}},{"kind":"Variable","span":{"file_name":"src/main.rs","byte_start":418,"byte_end":419,"line_start":18,"line_end":18,"column_start":17,"column_end":18},"ref_id":{"krate":0,"index":738197513}},{"kind":"Variable","span":{"file_name":"src/main.rs","byte_start":429,"byte_end":430,"line_start":18,"line_end":18,"column_start":28,"column_end":29},"ref_id":{"krate":0,"index":1946157065}},{"kind":"Variable","span":{"file_name":"src/main.rs","byte_start":455,"byte_end":456,"line_start":19,"line_end":19,"column_start":23,"column_end":24},"ref_id":{"krate":0,"index":1946157065}},{"kind":"Variable","span":{"file_name":"src/main.rs","byte_start":475,"byte_end":476,"line_start":20,"line_end":20,"column_start":18,"column_end":19},"ref_id":{"krate":2,"index":35951}},{"kind":"Variable","span":{"file_name":"src/main.rs","byte_start":478,"byte_end":479,"line_start":20,"line_end":20,"column_start":21,"column_end":22},"ref_id":{"krate":2,"index":35952}},{"kind":"Variable","span":{"file_name":"src/main.rs","byte_start":478,"byte_end":479,"line_start":20,"line_end":20,"column_start":21,"column_end":22},"ref_id":{"krate":0,"index":1946157065}},{"kind":"Variable","span":{"file_name":"src/main.rs","byte_start":470,"byte_end":471,"line_start":20,"line_end":20,"column_start":13,"column_end":14},"ref_id":{"krate":2,"index":37341}},{"kind":"Variable","span":{"file_name":"src/main.rs","byte_start":503,"byte_end":504,"line_start":21,"line_end":21,"column_start":22,"column_end":23},"ref_id":{"krate":2,"index":35951}},{"kind":"Variable","span":{"file_name":"src/main.rs","byte_start":503,"byte_end":504,"line_start":21,"line_end":21,"column_start":22,"column_end":23},"ref_id":{"krate":0,"index":2516582409}},{"kind":"Variable","span":{"file_name":"src/main.rs","byte_start":506,"byte_end":507,"line_start":21,"line_end":21,"column_start":25,"column_end":26},"ref_id":{"krate":2,"index":35952}},{"kind":"Variable","span":{"file_name":"src/main.rs","byte_start":506,"byte_end":507,"line_start":21,"line_end":21,"column_start":25,"column_end":26},"ref_id":{"krate":0,"index":1946157065}},{"kind":"Variable","span":{"file_name":"src/main.rs","byte_start":498,"byte_end":499,"line_start":21,"line_end":21,"column_start":17,"column_end":18},"ref_id":{"krate":2,"index":37341}},{"kind":"Variable","span":{"file_name":"src/main.rs","byte_start":570,"byte_end":571,"line_start":23,"line_end":23,"column_start":26,"column_end":27},"ref_id":{"krate":0,"index":2516582409}},{"kind":"Variable","span":{"file_name":"src/main.rs","byte_start":574,"byte_end":575,"line_start":23,"line_end":23,"column_start":30,"column_end":31},"ref_id":{"krate":0,"index":2432696329}},{"kind":"Variable","span":{"file_name":"src/main.rs","byte_start":565,"byte_end":566,"line_start":23,"line_end":23,"column_start":21,"column_end":22},"ref_id":{"krate":2,"index":37341}},{"kind":"Variable","span":{"file_name":"src/main.rs","byte_start":601,"byte_end":602,"line_start":24,"line_end":24,"column_start":24,"column_end":25},"ref_id":{"krate":0,"index":738197513}},{"kind":"Variable","span":{"file_name":"src/main.rs","byte_start":603,"byte_end":604,"line_start":24,"line_end":24,"column_start":26,"column_end":27},"ref_id":{"krate":0,"index":889192457}},{"kind":"Variable","span":{"file_name":"src/main.rs","byte_start":614,"byte_end":615,"line_start":24,"line_end":24,"column_start":37,"column_end":38},"ref_id":{"krate":0,"index":738197513}},{"kind":"Variable","span":{"file_name":"src/main.rs","byte_start":616,"byte_end":617,"line_start":24,"line_end":24,"column_start":39,"column_end":40},"ref_id":{"krate":0,"index":889192457}},{"kind":"Variable","span":{"file_name":"src/main.rs","byte_start":622,"byte_end":623,"line_start":24,"line_end":24,"column_start":45,"column_end":46},"ref_id":{"krate":0,"index":1946157065}},{"kind":"Variable","span":{"file_name":"src/main.rs","byte_start":650,"byte_end":652,"line_start":25,"line_end":25,"column_start":25,"column_end":27},"ref_id":{"krate":0,"index":1895825417}},{"kind":"Variable","span":{"file_name":"src/main.rs","byte_start":752,"byte_end":754,"line_start":29,"line_end":29,"column_start":20,"column_end":22},"ref_id":{"krate":0,"index":1895825417}},{"kind":"Variable","span":{"file_name":"src/main.rs","byte_start":780,"byte_end":783,"line_start":30,"line_end":30,"column_start":24,"column_end":27},"ref_id":{"krate":0,"index":3523215369}},{"kind":"Variable","span":{"file_name":"src/main.rs","byte_start":786,"byte_end":787,"line_start":30,"line_end":30,"column_start":30,"column_end":31},"ref_id":{"krate":0,"index":1946157065}},{"kind":"Variable","span":{"file_name":"src/main.rs","byte_start":791,"byte_end":792,"line_start":30,"line_end":30,"column_start":35,"column_end":36},"ref_id":{"krate":0,"index":2432696329}},{"kind":"Variable","span":{"file_name":"src/main.rs","byte_start":795,"byte_end":796,"line_start":30,"line_end":30,"column_start":39,"column_end":40},"ref_id":{"krate":0,"index":2516582409}},{"kind":"Variable","span":{"file_name":"src/main.rs","byte_start":834,"byte_end":835,"line_start":31,"line_end":31,"column_start":31,"column_end":32},"ref_id":{"krate":0,"index":1946157065}},{"kind":"Variable","span":{"file_name":"src/main.rs","byte_start":839,"byte_end":840,"line_start":31,"line_end":31,"column_start":36,"column_end":37},"ref_id":{"krate":0,"index":2432696329}},{"kind":"Variable","span":{"file_name":"src/main.rs","byte_start":843,"byte_end":844,"line_start":31,"line_end":31,"column_start":40,"column_end":41},"ref_id":{"krate":0,"index":2516582409}},{"kind":"Variable","span":{"file_name":"src/main.rs","byte_start":828,"byte_end":831,"line_start":31,"line_end":31,"column_start":25,"column_end":28},"ref_id":{"krate":0,"index":3523215369}},{"kind":"Variable","span":{"file_name":"src/main.rs","byte_start":938,"byte_end":941,"line_start":36,"line_end":36,"column_start":24,"column_end":27},"ref_id":{"krate":0,"index":3523215369}}],"macro_refs":[],"relations":[]}